fabric_ceph_client/__init__.py
fabric_ceph_client/ceph_fs_mount_bundle.py
fabric_ceph_client/fabric_ceph_client.py
fabric_ceph_client-1.0.2.dist-info/licenses/LICENSE
fabric_ceph_client-1.0.2.dist-info/WHEEL
fabric_ceph_client-1.0.2.dist-info/METADATA
fabric_ceph_client-1.0.2.dist-info/RECORD
