Metadata-Version: 2.4
Name: fabric_ceph_client
Version: 1.0.2
Summary: FABRIC Ceph Manager Client API
Author-email: Komal Thareja <kthare10@renci.org>
Requires-Python: >=3.8
License-File: LICENSE
Requires-Dist: requests
